{"stats":{"minecraft:dropped":{"minecraft:peony":2},"minecraft:mined":{"minecraft:short_grass":1,"minecraft:oak_log":3,"minecraft:oak_leaves":1},"minecraft:custom":{"minecraft:jump":249,"minecraft:leave_game":1,"minecraft:time_since_rest":18977,"minecraft:damage_dealt":493,"minecraft:crouch_one_cm":1377,"minecraft:sprint_one_cm":8315,"minecraft:play_time":18977,"minecraft:damage_taken":524,"minecraft:time_since_death":18977,"minecraft:walk_one_cm":22028,"minecraft:sneak_time":1451,"minecraft:total_world_time":18977,"minecraft:damage_resisted":1508,"minecraft:drop":2,"minecraft:fall_one_cm":2054,"minecraft:fly_one_cm":9886},"minecraft:picked_up":{"minecraft:oak_log":3,"minecraft:oak_sapling":1,"minecraft:peony":2}},"DataVersion":3953}